hychain/__cli__.py
hychain/__init__.py
hychain/_version.py
hychain/conf/__init__.py
hychain/conf/about/hychain.yaml
hychain/py.typed
hyfi_chain-0.1.0.dist-info/LICENSE
hyfi_chain-0.1.0.dist-info/METADATA
hyfi_chain-0.1.0.dist-info/WHEEL
hyfi_chain-0.1.0.dist-info/entry_points.txt
hyfi_chain-0.1.0.dist-info/RECORD
